{
  "fantasy_content": {
    "xml:lang": "en-US",
    "yahoo:uri": "/fantasy/v2/league/458.l.17400/players;status=FA;sort=AR;sort_type=lastweek;start=150;count=25",
    "league": [
      {
        "league_key": "458.l.17400",
        "league_id": "17400",
        "name": "The Big Man Hit the Ball Far!",
        "url": "https://baseball.fantasysports.yahoo.com/b1/17400",
        "logo_url": "https://yahoofantasysports-res.cloudinary.com/image/upload/t_s192sq/fantasy-logos/24672848913_a81bd3b136.jpg",
        "draft_status": "postdraft",
        "num_teams": 10,
        "edit_key": "2025-09-03",
        "weekly_deadline": "",
        "league_update_timestamp": "1756799478",
        "scoring_type": "head",
        "league_type": "private",
        "renew": "431_84492",
        "renewed": "",
        "felo_tier": "silver",
        "matchup_week": 22,
        "iris_group_chat_id": "",
        "allow_add_to_dl_extra_pos": 1,
        "is_pro_league": "0",
        "is_cash_league": "0",
        "current_week": 22,
        "start_week": "1",
        "start_date": "2025-03-18",
        "end_week": "24",
        "end_date": "2025-09-21",
        "is_plus_league": "0",
        "game_code": "mlb",
        "season": "2025"
      },
      {
        "players": {
          "0": {
            "player": [
              [
                {
                  "player_key": "458.p.63484"
                },
                {
                  "player_id": "63484"
                },
                {
                  "name": {
                    "full": "Kai-Wei Teng",
                    "first": "Kai-Wei",
                    "last": "Teng",
                    "ascii_first": "Kai-Wei",
                    "ascii_last": "Teng"
                  }
                },
                {
                  "url": "https://sports.yahoo.com/mlb/players/63484"
                },
                {
                  "editorial_player_key": "mlb.p.63484"
                },
                {
                  "editorial_team_key": "mlb.t.26"
                },
                {
                  "editorial_team_full_name": "San Francisco Giants"
                },
                {
                  "editorial_team_abbr": "SF"
                },
                {
                  "editorial_team_url": "https://sports.yahoo.com/mlb/teams/san-francisco/"
                },
                {
                  "is_keeper": {
                    "status": false,
                    "cost": false,
                    "kept": false
                  }
                },
                {
                  "uniform_number": "66"
                },
                {
                  "display_position": "SP,RP"
                },
                {
                  "headshot": {
                    "url": "https://s.yimg.com/iu/api/res/1.2/0g3kUXqvTyJJyrdmGH9GGQ--~C/YXBwaWQ9eXNwb3J0cztjaD0yMzM2O2NyPTE7Y3c9MTc5MDtkeD04NTc7ZHk9MDtmaT11bGNyb3A7aD02MDtxPTEwMDt3PTQ2/https://s.yimg.com/xe/i/us/sp/v/mlb_cutout/players_l/03052024/63484.png",
                    "size": "small"
                  },
                  "image_url": "https://s.yimg.com/iu/api/res/1.2/0g3kUXqvTyJJyrdmGH9GGQ--~C/YXBwaWQ9eXNwb3J0cztjaD0yMzM2O2NyPTE7Y3c9MTc5MDtkeD04NTc7ZHk9MDtmaT11bGNyb3A7aD02MDtxPTEwMDt3PTQ2/https://s.yimg.com/xe/i/us/sp/v/mlb_cutout/players_l/03052024/63484.png"
                },
                {
                  "is_undroppable": "0"
                },
                {
                  "position_type": "P"
                },
                {
                  "primary_position": "SP"
                },
                {
                  "eligible_positions": [
                    {
                      "position": "SP"
                    },
                    {
                      "position": "RP"
                    },
                    {
                      "position": "P"
                    }
                  ]
                },
                {
                  "eligible_positions_to_add": []
                },
                [],
                [],
                {
                  "has_player_notes": 1
                },
                {
                  "has_recent_player_notes": 1
                },
                {
                  "player_notes_last_timestamp": 1756770449
                }
              ]
            ]
          },
          "1": {
            "player": [
              [
                {
                  "player_key": "458.p.60569"
                },
                {
                  "player_id": "60569"
                },
                {
                  "name": {
                    "full": "Evan Sisk",
                    "first": "Evan",
                    "last": "Sisk",
                    "ascii_first": "Evan",
                    "ascii_last": "Sisk"
                  }
                },
                {
                  "url": "https://sports.yahoo.com/mlb/players/60569"
                },
                {
                  "editorial_player_key": "mlb.p.60569"
                },
                {
                  "editorial_team_key": "mlb.t.23"
                },
                {
                  "editorial_team_full_name": "Pittsburgh Pirates"
                },
                {
                  "editorial_team_abbr": "PIT"
                },
                {
                  "editorial_team_url": "https://sports.yahoo.com/mlb/teams/pittsburgh/"
                },
                {
                  "is_keeper": {
                    "status": false,
                    "cost": false,
                    "kept": false
                  }
                },
                {
                  "uniform_number": "51"
                },
                {
                  "display_position": "RP"
                },
                {
                  "headshot": {
                    "url": "https://s.yimg.com/iu/api/res/1.2/BO._g1SrJzDc4Fa5SMyrOA--~C/YXBwaWQ9eXNwb3J0cztjaD0yMzM2O2NyPTE7Y3c9MTc5MDtkeD04NTc7ZHk9MDtmaT11bGNyb3A7aD02MDtxPTEwMDt3PTQ2/https://s.yimg.com/xe/i/us/sp/v/mlb_cutout/players_l/03242025/60569.png",
                    "size": "small"
                  },
                  "image_url": "https://s.yimg.com/iu/api/res/1.2/BO._g1SrJzDc4Fa5SMyrOA--~C/YXBwaWQ9eXNwb3J0cztjaD0yMzM2O2NyPTE7Y3c9MTc5MDtkeD04NTc7ZHk9MDtmaT11bGNyb3A7aD02MDtxPTEwMDt3PTQ2/https://s.yimg.com/xe/i/us/sp/v/mlb_cutout/players_l/03242025/60569.png"
                },
                {
                  "is_undroppable": "0"
                },
                {
                  "position_type": "P"
                },
                {
                  "primary_position": "RP"
                },
                {
                  "eligible_positions": [
                    {
                      "position": "RP"
                    },
                    {
                      "position": "P"
                    }
                  ]
                },
                {
                  "eligible_positions_to_add": []
                },
                [],
                [],
                {
                  "has_player_notes": 1
                },
                [],
                {
                  "player_notes_last_timestamp": 1756501860
                }
              ]
            ]
          },
          "2": {
            "player": [
              [
                {
                  "player_key": "458.p.64814"
                },
                {
                  "player_id": "64814"
                },
                {
                  "name": {
                    "full": "Travis Adams",
                    "first": "Travis",
                    "last": "Adams",
                    "ascii_first": "Travis",
                    "ascii_last": "Adams"
                  }
                },
                {
                  "url": "https://sports.yahoo.com/mlb/players/64814"
                },
                {
                  "editorial_player_key": "mlb.p.64814"
                },
                {
                  "editorial_team_key": "mlb.t.9"
                },
                {
                  "editorial_team_full_name": "Minnesota Twins"
                },
                {
                  "editorial_team_abbr": "MIN"
                },
                {
                  "editorial_team_url": "https://sports.yahoo.com/mlb/teams/minnesota/"
                },
                {
                  "is_keeper": {
                    "status": false,
                    "cost": false,
                    "kept": false
                  }
                },
                {
                  "uniform_number": "45"
                },
                {
                  "display_position": "SP,RP"
                },
                {
                  "headshot": {
                    "url": "https://s.yimg.com/iu/api/res/1.2/TcM85WhJ.fAOHWf2QKLjIw--~C/YXBwaWQ9eXNwb3J0cztjaD0yMDA7Y3I9MTtjdz0xNTM7ZHg9NzQ7ZHk9MDtmaT11bGNyb3A7aD02MDtxPTEwMDt3PTQ2/https://s.yimg.com/dh/ap/default/140828/silhouette@2x.png",
                    "size": "small"
                  },
                  "image_url": "https://s.yimg.com/iu/api/res/1.2/TcM85WhJ.fAOHWf2QKLjIw--~C/YXBwaWQ9eXNwb3J0cztjaD0yMDA7Y3I9MTtjdz0xNTM7ZHg9NzQ7ZHk9MDtmaT11bGNyb3A7aD02MDtxPTEwMDt3PTQ2/https://s.yimg.com/dh/ap/default/140828/silhouette@2x.png"
                },
                {
                  "is_undroppable": "0"
                },
                {
                  "position_type": "P"
                },
                {
                  "primary_position": "SP"
                },
                {
                  "eligible_positions": [
                    {
                      "position": "SP"
                    },
                    {
                      "position": "RP"
                    },
                    {
                      "position": "P"
                    }
                  ]
                },
                {
                  "eligible_positions_to_add": []
                },
                [],
                [],
                {
                  "has_player_notes": 1
                },
                {
                  "has_recent_player_notes": 1
                },
                {
                  "player_notes_last_timestamp": 1756745543
                }
              ]
            ]
          },
          "3": {
            "player": [
              [
                {
                  "player_key": "458.p.11889"
                },
                {
                  "player_id": "11889"
                },
                {
                  "name": {
                    "full": "Ryan Thompson",
                    "first": "Ryan",
                    "last": "Thompson",
                    "ascii_first": "Ryan",
                    "ascii_last": "Thompson"
                  }
                },
                {
                  "url": "https://sports.yahoo.com/mlb/players/11889"
                },
                {
                  "editorial_player_key": "mlb.p.11889"
                },
                {
                  "editorial_team_key": "mlb.t.29"
                },
                {
                  "editorial_team_full_name": "Arizona Diamondbacks"
                },
                {
                  "editorial_team_abbr": "AZ"
                },
                {
                  "editorial_team_url": "https://sports.yahoo.com/mlb/teams/arizona/"
                },
                {
                  "is_keeper": {
                    "status": false,
                    "cost": false,
                    "kept": false
                  }
                },
                {
                  "uniform_number": "81"
                },
                {
                  "display_position": "RP"
                },
                {
                  "headshot": {
                    "url": "https://s.yimg.com/iu/api/res/1.2/4Rda3mDZtkdXh5NTr2.mYA--~C/YXBwaWQ9eXNwb3J0cztjaD0yMzM2O2NyPTE7Y3c9MTc5MDtkeD04NTc7ZHk9MDtmaT11bGNyb3A7aD02MDtxPTEwMDt3PTQ2/https://s.yimg.com/xe/i/us/sp/v/mlb_cutout/players_l/03172025/11889.png",
                    "size": "small"
                  },
                  "image_url": "https://s.yimg.com/iu/api/res/1.2/4Rda3mDZtkdXh5NTr2.mYA--~C/YXBwaWQ9eXNwb3J0cztjaD0yMzM2O2NyPTE7Y3c9MTc5MDtkeD04NTc7ZHk9MDtmaT11bGNyb3A7aD02MDtxPTEwMDt3PTQ2/https://s.yimg.com/xe/i/us/sp/v/mlb_cutout/players_l/03172025/11889.png"
                },
                {
                  "is_undroppable": "0"
                },
                {
                  "position_type": "P"
                },
                {
                  "primary_position": "RP"
                },
                {
                  "eligible_positions": [
                    {
                      "position": "RP"
                    },
                    {
                      "position": "P"
                    }
                  ]
                },
                {
                  "eligible_positions_to_add": []
                },
                [],
                [],
                {
                  "has_player_notes": 1
                },
                {
                  "has_recent_player_notes": 1
                },
                {
                  "player_notes_last_timestamp": 1756763220
                }
              ]
            ]
          },
          "4": {
            "player": [
              [
                {
                  "player_key": "458.p.62601"
                },
                {
                  "player_id": "62601"
                },
                {
                  "name": {
                    "full": "Luis Curvelo",
                    "first": "Luis",
                    "last": "Curvelo",
                    "ascii_first": "Luis",
                    "ascii_last": "Curvelo"
                  }
                },
                {
                  "url": "https://sports.yahoo.com/mlb/players/62601"
                },
                {
                  "editorial_player_key": "mlb.p.62601"
                },
                {
                  "editorial_team_key": "mlb.t.13"
                },
                {
                  "editorial_team_full_name": "Texas Rangers"
                },
                {
                  "editorial_team_abbr": "TEX"
                },
                {
                  "editorial_team_url": "https://sports.yahoo.com/mlb/teams/texas/"
                },
                {
                  "is_keeper": {
                    "status": false,
                    "cost": false,
                    "kept": false
                  }
                },
                {
                  "uniform_number": "57"
                },
                {
                  "display_position": "RP"
                },
                {
                  "headshot": {
                    "url": "https://s.yimg.com/iu/api/res/1.2/mrSyaOdmjs7KUh4YJhIZig--~C/YXBwaWQ9eXNwb3J0cztjaD0yMzM2O2NyPTE7Y3c9MTc5MDtkeD04NTc7ZHk9MDtmaT11bGNyb3A7aD02MDtxPTEwMDt3PTQ2/https://s.yimg.com/xe/i/us/sp/v/mlb_cutout/players_l/03282025/62601.png",
                    "size": "small"
                  },
                  "image_url": "https://s.yimg.com/iu/api/res/1.2/mrSyaOdmjs7KUh4YJhIZig--~C/YXBwaWQ9eXNwb3J0cztjaD0yMzM2O2NyPTE7Y3c9MTc5MDtkeD04NTc7ZHk9MDtmaT11bGNyb3A7aD02MDtxPTEwMDt3PTQ2/https://s.yimg.com/xe/i/us/sp/v/mlb_cutout/players_l/03282025/62601.png"
                },
                {
                  "is_undroppable": "0"
                },
                {
                  "position_type": "P"
                },
                {
                  "primary_position": "RP"
                },
                {
                  "eligible_positions": [
                    {
                      "position": "RP"
                    },
                    {
                      "position": "P"
                    }
                  ]
                },
                {
                  "eligible_positions_to_add": []
                },
                [],
                [],
                [],
                [],
                []
              ]
            ]
          },
          "5": {
            "player": [
              [
                {
                  "player_key": "458.p.10775"
                },
                {
                  "player_id": "10775"
                },
                {
                  "name": {
                    "full": "Kyle Farmer",
                    "first": "Kyle",
                    "last": "Farmer",
                    "ascii_first": "Kyle",
                    "ascii_last": "Farmer"
                  }
                },
                {
                  "url": "https://sports.yahoo.com/mlb/players/10775"
                },
                {
                  "editorial_player_key": "mlb.p.10775"
                },
                {
                  "editorial_team_key": "mlb.t.27"
                },
                {
                  "editorial_team_full_name": "Colorado Rockies"
                },
                {
                  "editorial_team_abbr": "COL"
                },
                {
                  "editorial_team_url": "https://sports.yahoo.com/mlb/teams/colorado/"
                },
                {
                  "is_keeper": {
                    "status": false,
                    "cost": false,
                    "kept": false
                  }
                },
                {
                  "uniform_number": "6"
                },
                {
                  "display_position": "1B,2B,3B,SS"
                },
                {
                  "headshot": {
                    "url": "https://s.yimg.com/iu/api/res/1.2/zBbUQLRAIwG1heS_pSYKkQ--~C/YXBwaWQ9eXNwb3J0cztjaD0yMzM2O2NyPTE7Y3c9MTc5MDtkeD04NTc7ZHk9MDtmaT11bGNyb3A7aD02MDtxPTEwMDt3PTQ2/https://s.yimg.com/xe/i/us/sp/v/mlb_cutout/players_l/03202025/10775.png",
                    "size": "small"
                  },
                  "image_url": "https://s.yimg.com/iu/api/res/1.2/zBbUQLRAIwG1heS_pSYKkQ--~C/YXBwaWQ9eXNwb3J0cztjaD0yMzM2O2NyPTE7Y3c9MTc5MDtkeD04NTc7ZHk9MDtmaT11bGNyb3A7aD02MDtxPTEwMDt3PTQ2/https://s.yimg.com/xe/i/us/sp/v/mlb_cutout/players_l/03202025/10775.png"
                },
                {
                  "is_undroppable": "0"
                },
                {
                  "position_type": "B"
                },
                {
                  "primary_position": "1B"
                },
                {
                  "eligible_positions": [
                    {
                      "position": "1B"
                    },
                    {
                      "position": "2B"
                    },
                    {
                      "position": "3B"
                    },
                    {
                      "position": "SS"
                    },
                    {
                      "position": "Util"
                    }
                  ]
                },
                {
                  "eligible_positions_to_add": []
                },
                [],
                [],
                {
                  "has_player_notes": 1
                },
                [],
                {
                  "player_notes_last_timestamp": 1756557209
                }
              ]
            ]
          },
          "6": {
            "player": [
              [
                {
                  "player_key": "458.p.64330"
                },
                {
                  "player_id": "64330"
                },
                {
                  "name": {
                    "full": "Cam Smith",
                    "first": "Cam",
                    "last": "Smith",
                    "ascii_first": "Cam",
                    "ascii_last": "Smith"
                  }
                },
                {
                  "url": "https://sports.yahoo.com/mlb/players/64330"
                },
                {
                  "editorial_player_key": "mlb.p.64330"
                },
                {
                  "editorial_team_key": "mlb.t.18"
                },
                {
                  "editorial_team_full_name": "Houston Astros"
                },
                {
                  "editorial_team_abbr": "HOU"
                },
                {
                  "editorial_team_url": "https://sports.yahoo.com/mlb/teams/houston/"
                },
                {
                  "is_keeper": {
                    "status": false,
                    "cost": false,
                    "kept": false
                  }
                },
                {
                  "uniform_number": "11"
                },
                {
                  "display_position": "3B,OF"
                },
                {
                  "headshot": {
                    "url": "https://s.yimg.com/iu/api/res/1.2/PIWhmRM.BMJwG0Wm5X2wkA--~C/YXBwaWQ9eXNwb3J0cztjaD0yMzM2O2NyPTE7Y3c9MTc5MDtkeD04NTc7ZHk9MDtmaT11bGNyb3A7aD02MDtxPTEwMDt3PTQ2/https://s.yimg.com/xe/i/us/sp/v/mlb_cutout/players_l/03212025/64330.png",
                    "size": "small"
                  },
                  "image_url": "https://s.yimg.com/iu/api/res/1.2/PIWhmRM.BMJwG0Wm5X2wkA--~C/YXBwaWQ9eXNwb3J0cztjaD0yMzM2O2NyPTE7Y3c9MTc5MDtkeD04NTc7ZHk9MDtmaT11bGNyb3A7aD02MDtxPTEwMDt3PTQ2/https://s.yimg.com/xe/i/us/sp/v/mlb_cutout/players_l/03212025/64330.png"
                },
                {
                  "is_undroppable": "0"
                },
                {
                  "position_type": "B"
                },
                {
                  "primary_position": "3B"
                },
                {
                  "eligible_positions": [
                    {
                      "position": "3B"
                    },
                    {
                      "position": "OF"
                    },
                    {
                      "position": "Util"
                    }
                  ]
                },
                {
                  "eligible_positions_to_add": []
                },
                [],
                [],
                {
                  "has_player_notes": 1
                },
                {
                  "has_recent_player_notes": 1
                },
                {
                  "player_notes_last_timestamp": 1756792950
                }
              ]
            ]
          },
          "7": {
            "player": [
              [
                {
                  "player_key": "458.p.12769"
                },
                {
                  "player_id": "12769"
                },
                {
                  "name": {
                    "full": "Nic Enright",
                    "first": "Nic",
                    "last": "Enright",
                    "ascii_first": "Nic",
                    "ascii_last": "Enright"
                  }
                },
                {
                  "url": "https://sports.yahoo.com/mlb/players/12769"
                },
                {
                  "editorial_player_key": "mlb.p.12769"
                },
                {
                  "editorial_team_key": "mlb.t.5"
                },
                {
                  "editorial_team_full_name": "Cleveland Guardians"
                },
                {
                  "editorial_team_abbr": "CLE"
                },
                {
                  "editorial_team_url": "https://sports.yahoo.com/mlb/teams/cleveland/"
                },
                {
                  "is_keeper": {
                    "status": false,
                    "cost": false,
                    "kept": false
                  }
                },
                {
                  "uniform_number": "59"
                },
                {
                  "display_position": "RP"
                },
                {
                  "headshot": {
                    "url": "https://s.yimg.com/iu/api/res/1.2/6mlpJWuxYRrgIdvsnDSAFg--~C/YXBwaWQ9eXNwb3J0cztjaD0yMzM2O2NyPTE7Y3c9MTc5MDtkeD04NTc7ZHk9MDtmaT11bGNyb3A7aD02MDtxPTEwMDt3PTQ2/https://s.yimg.com/xe/i/us/sp/v/mlb_cutout/players_l/03192025/12769.png",
                    "size": "small"
                  },
                  "image_url": "https://s.yimg.com/iu/api/res/1.2/6mlpJWuxYRrgIdvsnDSAFg--~C/YXBwaWQ9eXNwb3J0cztjaD0yMzM2O2NyPTE7Y3c9MTc5MDtkeD04NTc7ZHk9MDtmaT11bGNyb3A7aD02MDtxPTEwMDt3PTQ2/https://s.yimg.com/xe/i/us/sp/v/mlb_cutout/players_l/03192025/12769.png"
                },
                {
                  "is_undroppable": "0"
                },
                {
                  "position_type": "P"
                },
                {
                  "primary_position": "RP"
                },
                {
                  "eligible_positions": [
                    {
                      "position": "RP"
                    },
                    {
                      "position": "P"
                    }
                  ]
                },
                {
                  "eligible_positions_to_add": []
                },
                [],
                [],
                [],
                [],
                []
              ]
            ]
          },
          "8": {
            "player": [
              [
                {
                  "player_key": "458.p.63448"
                },
                {
                  "player_id": "63448"
                },
                {
                  "name": {
                    "full": "Michael Petersen",
                    "first": "Michael",
                    "last": "Petersen",
                    "ascii_first": "Michael",
                    "ascii_last": "Petersen"
                  }
                },
                {
                  "url": "https://sports.yahoo.com/mlb/players/63448"
                },
                {
                  "editorial_player_key": "mlb.p.63448"
                },
                {
                  "editorial_team_key": "mlb.t.28"
                },
                {
                  "editorial_team_full_name": "Miami Marlins"
                },
                {
                  "editorial_team_abbr": "MIA"
                },
                {
                  "editorial_team_url": "https://sports.yahoo.com/mlb/teams/miami/"
                },
                {
                  "is_keeper": {
                    "status": false,
                    "cost": false,
                    "kept": false
                  }
                },
                {
                  "uniform_number": "49"
                },
                {
                  "display_position": "RP"
                },
                {
                  "headshot": {
                    "url": "https://s.yimg.com/iu/api/res/1.2/Z3uskmeJBPzNmEf02G2f_g--~C/YXBwaWQ9eXNwb3J0cztjaD0yMzM2O2NyPTE7Y3c9MTc5MDtkeD04NTc7ZHk9MDtmaT11bGNyb3A7aD02MDtxPTEwMDt3PTQ2/https://s.yimg.com/xe/i/us/sp/v/mlb_cutout/players_l/06262025/63448.png",
                    "size": "small"
                  },
                  "image_url": "https://s.yimg.com/iu/api/res/1.2/Z3uskmeJBPzNmEf02G2f_g--~C/YXBwaWQ9eXNwb3J0cztjaD0yMzM2O2NyPTE7Y3c9MTc5MDtkeD04NTc7ZHk9MDtmaT11bGNyb3A7aD02MDtxPTEwMDt3PTQ2/https://s.yimg.com/xe/i/us/sp/v/mlb_cutout/players_l/06262025/63448.png"
                },
                {
                  "is_undroppable": "0"
                },
                {
                  "position_type": "P"
                },
                {
                  "primary_position": "RP"
                },
                {
                  "eligible_positions": [
                    {
                      "position": "RP"
                    },
                    {
                      "position": "P"
                    }
                  ]
                },
                {
                  "eligible_positions_to_add": []
                },
                [],
                [],
                {
                  "has_player_notes": 1
                },
                {
                  "has_recent_player_notes": 1
                },
                {
                  "player_notes_last_timestamp": 1756741334
                }
              ]
            ]
          },
          "9": {
            "player": [
              [
                {
                  "player_key": "458.p.9262"
                },
                {
                  "player_id": "9262"
                },
                {
                  "name": {
                    "full": "Brooks Raley",
                    "first": "Brooks",
                    "last": "Raley",
                    "ascii_first": "Brooks",
                    "ascii_last": "Raley"
                  }
                },
                {
                  "url": "https://sports.yahoo.com/mlb/players/9262"
                },
                {
                  "editorial_player_key": "mlb.p.9262"
                },
                {
                  "editorial_team_key": "mlb.t.21"
                },
                {
                  "editorial_team_full_name": "New York Mets"
                },
                {
                  "editorial_team_abbr": "NYM"
                },
                {
                  "editorial_team_url": "https://sports.yahoo.com/mlb/teams/ny-mets/"
                },
                {
                  "is_keeper": {
                    "status": false,
                    "cost": false,
                    "kept": false
                  }
                },
                {
                  "uniform_number": "25"
                },
                {
                  "display_position": "RP"
                },
                {
                  "headshot": {
                    "url": "https://s.yimg.com/iu/api/res/1.2/vcqct7JL8ITKR4yuNBTFxA--~C/YXBwaWQ9eXNwb3J0cztjaD0yMzM2O2NyPTE7Y3c9MTc5MDtkeD04NTc7ZHk9MDtmaT11bGNyb3A7aD02MDtxPTEwMDt3PTQ2/https://s.yimg.com/xe/i/us/sp/v/mlb_cutout/players_l/04032024/9262.png",
                    "size": "small"
                  },
                  "image_url": "https://s.yimg.com/iu/api/res/1.2/vcqct7JL8ITKR4yuNBTFxA--~C/YXBwaWQ9eXNwb3J0cztjaD0yMzM2O2NyPTE7Y3c9MTc5MDtkeD04NTc7ZHk9MDtmaT11bGNyb3A7aD02MDtxPTEwMDt3PTQ2/https://s.yimg.com/xe/i/us/sp/v/mlb_cutout/players_l/04032024/9262.png"
                },
                {
                  "is_undroppable": "0"
                },
                {
                  "position_type": "P"
                },
                {
                  "primary_position": "RP"
                },
                {
                  "eligible_positions": [
                    {
                      "position": "RP"
                    },
                    {
                      "position": "P"
                    }
                  ]
                },
                {
                  "eligible_positions_to_add": []
                },
                [],
                [],
                [],
                [],
                []
              ]
            ]
          },
          "10": {
            "player": [
              [
                {
                  "player_key": "458.p.10422"
                },
                {
                  "player_id": "10422"
                },
                {
                  "name": {
                    "full": "Kolby Allard",
                    "first": "Kolby",
                    "last": "Allard",
                    "ascii_first": "Kolby",
                    "ascii_last": "Allard"
                  }
                },
                {
                  "url": "https://sports.yahoo.com/mlb/players/10422"
                },
                {
                  "editorial_player_key": "mlb.p.10422"
                },
                {
                  "editorial_team_key": "mlb.t.5"
                },
                {
                  "editorial_team_full_name": "Cleveland Guardians"
                },
                {
                  "editorial_team_abbr": "CLE"
                },
                {
                  "editorial_team_url": "https://sports.yahoo.com/mlb/teams/cleveland/"
                },
                {
                  "is_keeper": {
                    "status": false,
                    "cost": false,
                    "kept": false
                  }
                },
                {
                  "uniform_number": "49"
                },
                {
                  "display_position": "SP,RP"
                },
                {
                  "headshot": {
                    "url": "https://s.yimg.com/iu/api/res/1.2/biLAghGCT431CcHVE6ZEAQ--~C/YXBwaWQ9eXNwb3J0cztjaD0yMzM2O2NyPTE7Y3c9MTc5MDtkeD04NTc7ZHk9MDtmaT11bGNyb3A7aD02MDtxPTEwMDt3PTQ2/https://s.yimg.com/xe/i/us/sp/v/mlb_cutout/players_l/06022025/10422.png",
                    "size": "small"
                  },
                  "image_url": "https://s.yimg.com/iu/api/res/1.2/biLAghGCT431CcHVE6ZEAQ--~C/YXBwaWQ9eXNwb3J0cztjaD0yMzM2O2NyPTE7Y3c9MTc5MDtkeD04NTc7ZHk9MDtmaT11bGNyb3A7aD02MDtxPTEwMDt3PTQ2/https://s.yimg.com/xe/i/us/sp/v/mlb_cutout/players_l/06022025/10422.png"
                },
                {
                  "is_undroppable": "0"
                },
                {
                  "position_type": "P"
                },
                {
                  "primary_position": "SP"
                },
                {
                  "eligible_positions": [
                    {
                      "position": "SP"
                    },
                    {
                      "position": "RP"
                    },
                    {
                      "position": "P"
                    }
                  ]
                },
                {
                  "eligible_positions_to_add": []
                },
                [],
                [],
                [],
                [],
                []
              ]
            ]
          },
          "11": {
            "player": [
              [
                {
                  "player_key": "458.p.10498"
                },
                {
                  "player_id": "10498"
                },
                {
                  "name": {
                    "full": "Jahmai Jones",
                    "first": "Jahmai",
                    "last": "Jones",
                    "ascii_first": "Jahmai",
                    "ascii_last": "Jones"
                  }
                },
                {
                  "url": "https://sports.yahoo.com/mlb/players/10498"
                },
                {
                  "editorial_player_key": "mlb.p.10498"
                },
                {
                  "editorial_team_key": "mlb.t.6"
                },
                {
                  "editorial_team_full_name": "Detroit Tigers"
                },
                {
                  "editorial_team_abbr": "DET"
                },
                {
                  "editorial_team_url": "https://sports.yahoo.com/mlb/teams/detroit/"
                },
                {
                  "is_keeper": {
                    "status": false,
                    "cost": false,
                    "kept": false
                  }
                },
                {
                  "uniform_number": "18"
                },
                {
                  "display_position": "OF"
                },
                {
                  "headshot": {
                    "url": "https://s.yimg.com/iu/api/res/1.2/b1GInIpdf2ciKGKolCrvBw--~C/YXBwaWQ9eXNwb3J0cztjaD0yMzM2O2NyPTE7Y3c9MTc5MDtkeD04NTc7ZHk9MDtmaT11bGNyb3A7aD02MDtxPTEwMDt3PTQ2/https://s.yimg.com/xe/i/us/sp/v/mlb_cutout/players_l/06232025/10498.1.png",
                    "size": "small"
                  },
                  "image_url": "https://s.yimg.com/iu/api/res/1.2/b1GInIpdf2ciKGKolCrvBw--~C/YXBwaWQ9eXNwb3J0cztjaD0yMzM2O2NyPTE7Y3c9MTc5MDtkeD04NTc7ZHk9MDtmaT11bGNyb3A7aD02MDtxPTEwMDt3PTQ2/https://s.yimg.com/xe/i/us/sp/v/mlb_cutout/players_l/06232025/10498.1.png"
                },
                {
                  "is_undroppable": "0"
                },
                {
                  "position_type": "B"
                },
                {
                  "primary_position": "OF"
                },
                {
                  "eligible_positions": [
                    {
                      "position": "OF"
                    },
                    {
                      "position": "Util"
                    }
                  ]
                },
                {
                  "eligible_positions_to_add": []
                },
                [],
                [],
                {
                  "has_player_notes": 1
                },
                {
                  "has_recent_player_notes": 1
                },
                {
                  "player_notes_last_timestamp": 1756761579
                }
              ]
            ]
          },
          "12": {
            "player": [
              [
                {
                  "player_key": "458.p.62256"
                },
                {
                  "player_id": "62256"
                },
                {
                  "name": {
                    "full": "Spencer Bivens",
                    "first": "Spencer",
                    "last": "Bivens",
                    "ascii_first": "Spencer",
                    "ascii_last": "Bivens"
                  }
                },
                {
                  "url": "https://sports.yahoo.com/mlb/players/62256"
                },
                {
                  "editorial_player_key": "mlb.p.62256"
                },
                {
                  "editorial_team_key": "mlb.t.26"
                },
                {
                  "editorial_team_full_name": "San Francisco Giants"
                },
                {
                  "editorial_team_abbr": "SF"
                },
                {
                  "editorial_team_url": "https://sports.yahoo.com/mlb/teams/san-francisco/"
                },
                {
                  "is_keeper": {
                    "status": false,
                    "cost": false,
                    "kept": false
                  }
                },
                {
                  "uniform_number": "76"
                },
                {
                  "display_position": "RP"
                },
                {
                  "headshot": {
                    "url": "https://s.yimg.com/iu/api/res/1.2/TfEy.8yXz91q62745YRCiA--~C/YXBwaWQ9eXNwb3J0cztjaD0yMzM2O2NyPTE7Y3c9MTc5MDtkeD04NTc7ZHk9MDtmaT11bGNyb3A7aD02MDtxPTEwMDt3PTQ2/https://s.yimg.com/xe/i/us/sp/v/mlb_cutout/players_l/03272025/62256.png",
                    "size": "small"
                  },
                  "image_url": "https://s.yimg.com/iu/api/res/1.2/TfEy.8yXz91q62745YRCiA--~C/YXBwaWQ9eXNwb3J0cztjaD0yMzM2O2NyPTE7Y3c9MTc5MDtkeD04NTc7ZHk9MDtmaT11bGNyb3A7aD02MDtxPTEwMDt3PTQ2/https://s.yimg.com/xe/i/us/sp/v/mlb_cutout/players_l/03272025/62256.png"
                },
                {
                  "is_undroppable": "0"
                },
                {
                  "position_type": "P"
                },
                {
                  "primary_position": "RP"
                },
                {
                  "eligible_positions": [
                    {
                      "position": "RP"
                    },
                    {
                      "position": "P"
                    }
                  ]
                },
                {
                  "eligible_positions_to_add": []
                },
                [],
                [],
                {
                  "has_player_notes": 1
                },
                [],
                {
                  "player_notes_last_timestamp": 1756686479
                }
              ]
            ]
          },
          "13": {
            "player": [
              [
                {
                  "player_key": "458.p.60239"
                },
                {
                  "player_id": "60239"
                },
                {
                  "name": {
                    "full": "Edgardo Henriquez",
                    "first": "Edgardo",
                    "last": "Henriquez",
                    "ascii_first": "Edgardo",
                    "ascii_last": "Henriquez"
                  }
                },
                {
                  "url": "https://sports.yahoo.com/mlb/players/60239"
                },
                {
                  "editorial_player_key": "mlb.p.60239"
                },
                {
                  "editorial_team_key": "mlb.t.19"
                },
                {
                  "editorial_team_full_name": "Los Angeles Dodgers"
                },
                {
                  "editorial_team_abbr": "LAD"
                },
                {
                  "editorial_team_url": "https://sports.yahoo.com/mlb/teams/la-dodgers/"
                },
                {
                  "is_keeper": {
                    "status": false,
                    "cost": false,
                    "kept": false
                  }
                },
                {
                  "uniform_number": "60"
                },
                {
                  "display_position": "RP"
                },
                {
                  "headshot": {
                    "url": "https://s.yimg.com/iu/api/res/1.2/0mDI00f6g8tP82PIymFzng--~C/YXBwaWQ9eXNwb3J0cztjaD0yMzM2O2NyPTE7Y3c9MTc5MDtkeD04NTc7ZHk9MDtmaT11bGNyb3A7aD02MDtxPTEwMDt3PTQ2/https://s.yimg.com/xe/i/us/sp/v/mlb_cutout/players_l/03102025/60239.png",
                    "size": "small"
                  },
                  "image_url": "https://s.yimg.com/iu/api/res/1.2/0mDI00f6g8tP82PIymFzng--~C/YXBwaWQ9eXNwb3J0cztjaD0yMzM2O2NyPTE7Y3c9MTc5MDtkeD04NTc7ZHk9MDtmaT11bGNyb3A7aD02MDtxPTEwMDt3PTQ2/https://s.yimg.com/xe/i/us/sp/v/mlb_cutout/players_l/03102025/60239.png"
                },
                {
                  "is_undroppable": "0"
                },
                {
                  "position_type": "P"
                },
                {
                  "primary_position": "RP"
                },
                {
                  "eligible_positions": [
                    {
                      "position": "RP"
                    },
                    {
                      "position": "P"
                    }
                  ]
                },
                {
                  "eligible_positions_to_add": []
                },
                [],
                [],
                [],
                [],
                []
              ]
            ]
          },
          "14": {
            "player": [
              [
                {
                  "player_key": "458.p.9782"
                },
                {
                  "player_id": "9782"
                },
                {
                  "name": {
                    "full": "Andrew Chafin",
                    "first": "Andrew",
                    "last": "Chafin",
                    "ascii_first": "Andrew",
                    "ascii_last": "Chafin"
                  }
                },
                {
                  "url": "https://sports.yahoo.com/mlb/players/9782"
                },
                {
                  "editorial_player_key": "mlb.p.9782"
                },
                {
                  "editorial_team_key": "mlb.t.3"
                },
                {
                  "editorial_team_full_name": "Los Angeles Angels"
                },
                {
                  "editorial_team_abbr": "LAA"
                },
                {
                  "editorial_team_url": "https://sports.yahoo.com/mlb/teams/la-angels/"
                },
                {
                  "is_keeper": {
                    "status": false,
                    "cost": false,
                    "kept": false
                  }
                },
                {
                  "uniform_number": "39"
                },
                {
                  "display_position": "RP"
                },
                {
                  "headshot": {
                    "url": "https://s.yimg.com/iu/api/res/1.2/M_VEgDD4j.wMCQ_FQnrYJg--~C/YXBwaWQ9eXNwb3J0cztjaD0yMzM2O2NyPTE7Y3c9MTc5MDtkeD04NTc7ZHk9MDtmaT11bGNyb3A7aD02MDtxPTEwMDt3PTQ2/https://s.yimg.com/xe/i/us/sp/v/mlb_cutout/players_l/05082025/9782.png",
                    "size": "small"
                  },
                  "image_url": "https://s.yimg.com/iu/api/res/1.2/M_VEgDD4j.wMCQ_FQnrYJg--~C/YXBwaWQ9eXNwb3J0cztjaD0yMzM2O2NyPTE7Y3c9MTc5MDtkeD04NTc7ZHk9MDtmaT11bGNyb3A7aD02MDtxPTEwMDt3PTQ2/https://s.yimg.com/xe/i/us/sp/v/mlb_cutout/players_l/05082025/9782.png"
                },
                {
                  "is_undroppable": "0"
                },
                {
                  "position_type": "P"
                },
                {
                  "primary_position": "RP"
                },
                {
                  "eligible_positions": [
                    {
                      "position": "RP"
                    },
                    {
                      "position": "P"
                    }
                  ]
                },
                {
                  "eligible_positions_to_add": []
                },
                [],
                [],
                [],
                [],
                []
              ]
            ]
          },
          "15": {
            "player": [
              [
                {
                  "player_key": "458.p.61279"
                },
                {
                  "player_id": "61279"
                },
                {
                  "name": {
                    "full": "Cade Gibson",
                    "first": "Cade",
                    "last": "Gibson",
                    "ascii_first": "Cade",
                    "ascii_last": "Gibson"
                  }
                },
                {
                  "url": "https://sports.yahoo.com/mlb/players/61279"
                },
                {
                  "editorial_player_key": "mlb.p.61279"
                },
                {
                  "editorial_team_key": "mlb.t.28"
                },
                {
                  "editorial_team_full_name": "Miami Marlins"
                },
                {
                  "editorial_team_abbr": "MIA"
                },
                {
                  "editorial_team_url": "https://sports.yahoo.com/mlb/teams/miami/"
                },
                {
                  "is_keeper": {
                    "status": false,
                    "cost": false,
                    "kept": false
                  }
                },
                {
                  "uniform_number": "58"
                },
                {
                  "display_position": "SP,RP"
                },
                {
                  "headshot": {
                    "url": "https://s.yimg.com/iu/api/res/1.2/TcM85WhJ.fAOHWf2QKLjIw--~C/YXBwaWQ9eXNwb3J0cztjaD0yMDA7Y3I9MTtjdz0xNTM7ZHg9NzQ7ZHk9MDtmaT11bGNyb3A7aD02MDtxPTEwMDt3PTQ2/https://s.yimg.com/dh/ap/default/140828/silhouette@2x.png",
                    "size": "small"
                  },
                  "image_url": "https://s.yimg.com/iu/api/res/1.2/TcM85WhJ.fAOHWf2QKLjIw--~C/YXBwaWQ9eXNwb3J0cztjaD0yMDA7Y3I9MTtjdz0xNTM7ZHg9NzQ7ZHk9MDtmaT11bGNyb3A7aD02MDtxPTEwMDt3PTQ2/https://s.yimg.com/dh/ap/default/140828/silhouette@2x.png"
                },
                {
                  "is_undroppable": "0"
                },
                {
                  "position_type": "P"
                },
                {
                  "primary_position": "SP"
                },
                {
                  "eligible_positions": [
                    {
                      "position": "SP"
                    },
                    {
                      "position": "RP"
                    },
                    {
                      "position": "P"
                    }
                  ]
                },
                {
                  "eligible_positions_to_add": []
                },
                [],
                [],
                [],
                [],
                []
              ]
            ]
          },
          "16": {
            "player": [
              [
                {
                  "player_key": "458.p.10877"
                },
                {
                  "player_id": "10877"
                },
                {
                  "name": {
                    "full": "Jake Burger",
                    "first": "Jake",
                    "last": "Burger",
                    "ascii_first": "Jake",
                    "ascii_last": "Burger"
                  }
                },
                {
                  "url": "https://sports.yahoo.com/mlb/players/10877"
                },
                {
                  "editorial_player_key": "mlb.p.10877"
                },
                {
                  "editorial_team_key": "mlb.t.13"
                },
                {
                  "editorial_team_full_name": "Texas Rangers"
                },
                {
                  "editorial_team_abbr": "TEX"
                },
                {
                  "editorial_team_url": "https://sports.yahoo.com/mlb/teams/texas/"
                },
                {
                  "is_keeper": {
                    "status": true,
                    "cost": false,
                    "kept": true
                  }
                },
                {
                  "uniform_number": "21"
                },
                {
                  "display_position": "1B,3B"
                },
                {
                  "headshot": {
                    "url": "https://s.yimg.com/iu/api/res/1.2/h5zj7TlDossp4kEMjnZGkw--~C/YXBwaWQ9eXNwb3J0cztjaD0yMzM2O2NyPTE7Y3c9MTc5MDtkeD04NTc7ZHk9MDtmaT11bGNyb3A7aD02MDtxPTEwMDt3PTQ2/https://s.yimg.com/xe/i/us/sp/v/mlb_cutout/players_l/03042025/10877.png",
                    "size": "small"
                  },
                  "image_url": "https://s.yimg.com/iu/api/res/1.2/h5zj7TlDossp4kEMjnZGkw--~C/YXBwaWQ9eXNwb3J0cztjaD0yMzM2O2NyPTE7Y3c9MTc5MDtkeD04NTc7ZHk9MDtmaT11bGNyb3A7aD02MDtxPTEwMDt3PTQ2/https://s.yimg.com/xe/i/us/sp/v/mlb_cutout/players_l/03042025/10877.png"
                },
                {
                  "is_undroppable": "0"
                },
                {
                  "position_type": "B"
                },
                {
                  "primary_position": "1B"
                },
                {
                  "eligible_positions": [
                    {
                      "position": "1B"
                    },
                    {
                      "position": "3B"
                    },
                    {
                      "position": "Util"
                    }
                  ]
                },
                {
                  "eligible_positions_to_add": []
                },
                [],
                [],
                {
                  "has_player_notes": 1
                },
                {
                  "has_recent_player_notes": 1
                },
                {
                  "player_notes_last_timestamp": 1756765392
                }
              ]
            ]
          },
          "17": {
            "player": [
              [
                {
                  "player_key": "458.p.11453"
                },
                {
                  "player_id": "11453"
                },
                {
                  "name": {
                    "full": "Rico Garcia",
                    "first": "Rico",
                    "last": "Garcia",
                    "ascii_first": "Rico",
                    "ascii_last": "Garcia"
                  }
                },
                {
                  "url": "https://sports.yahoo.com/mlb/players/11453"
                },
                {
                  "editorial_player_key": "mlb.p.11453"
                },
                {
                  "editorial_team_key": "mlb.t.1"
                },
                {
                  "editorial_team_full_name": "Baltimore Orioles"
                },
                {
                  "editorial_team_abbr": "BAL"
                },
                {
                  "editorial_team_url": "https://sports.yahoo.com/mlb/teams/baltimore/"
                },
                {
                  "is_keeper": {
                    "status": false,
                    "cost": false,
                    "kept": false
                  }
                },
                {
                  "uniform_number": "50"
                },
                {
                  "display_position": "RP"
                },
                {
                  "headshot": {
                    "url": "https://s.yimg.com/iu/api/res/1.2/4PZzsZMm8kW0imyhJym_gQ--~C/YXBwaWQ9eXNwb3J0cztjaD0yMzM2O2NyPTE7Y3c9MTc5MDtkeD04NTc7ZHk9MDtmaT11bGNyb3A7aD02MDtxPTEwMDt3PTQ2/https://s.yimg.com/xe/i/us/sp/v/mlb_cutout/players_l/07232025/11453.png",
                    "size": "small"
                  },
                  "image_url": "https://s.yimg.com/iu/api/res/1.2/4PZzsZMm8kW0imyhJym_gQ--~C/YXBwaWQ9eXNwb3J0cztjaD0yMzM2O2NyPTE7Y3c9MTc5MDtkeD04NTc7ZHk9MDtmaT11bGNyb3A7aD02MDtxPTEwMDt3PTQ2/https://s.yimg.com/xe/i/us/sp/v/mlb_cutout/players_l/07232025/11453.png"
                },
                {
                  "is_undroppable": "0"
                },
                {
                  "position_type": "P"
                },
                {
                  "primary_position": "RP"
                },
                {
                  "eligible_positions": [
                    {
                      "position": "RP"
                    },
                    {
                      "position": "P"
                    }
                  ]
                },
                {
                  "eligible_positions_to_add": []
                },
                [],
                [],
                [],
                [],
                []
              ]
            ]
          },
          "18": {
            "player": [
              [
                {
                  "player_key": "458.p.11926"
                },
                {
                  "player_id": "11926"
                },
                {
                  "name": {
                    "full": "Reid Detmers",
                    "first": "Reid",
                    "last": "Detmers",
                    "ascii_first": "Reid",
                    "ascii_last": "Detmers"
                  }
                },
                {
                  "url": "https://sports.yahoo.com/mlb/players/11926"
                },
                {
                  "editorial_player_key": "mlb.p.11926"
                },
                {
                  "editorial_team_key": "mlb.t.3"
                },
                {
                  "editorial_team_full_name": "Los Angeles Angels"
                },
                {
                  "editorial_team_abbr": "LAA"
                },
                {
                  "editorial_team_url": "https://sports.yahoo.com/mlb/teams/la-angels/"
                },
                {
                  "is_keeper": {
                    "status": false,
                    "cost": false,
                    "kept": false
                  }
                },
                {
                  "uniform_number": "48"
                },
                {
                  "display_position": "SP,RP"
                },
                {
                  "headshot": {
                    "url": "https://s.yimg.com/iu/api/res/1.2/khE_bJkVdYMmC9K.pfa9Kw--~C/YXBwaWQ9eXNwb3J0cztjaD0yMzM2O2NyPTE7Y3c9MTc5MDtkeD04NTc7ZHk9MDtmaT11bGNyb3A7aD02MDtxPTEwMDt3PTQ2/https://s.yimg.com/xe/i/us/sp/v/mlb_cutout/players_l/04222024/11926.png",
                    "size": "small"
                  },
                  "image_url": "https://s.yimg.com/iu/api/res/1.2/khE_bJkVdYMmC9K.pfa9Kw--~C/YXBwaWQ9eXNwb3J0cztjaD0yMzM2O2NyPTE7Y3c9MTc5MDtkeD04NTc7ZHk9MDtmaT11bGNyb3A7aD02MDtxPTEwMDt3PTQ2/https://s.yimg.com/xe/i/us/sp/v/mlb_cutout/players_l/04222024/11926.png"
                },
                {
                  "is_undroppable": "0"
                },
                {
                  "position_type": "P"
                },
                {
                  "primary_position": "SP"
                },
                {
                  "eligible_positions": [
                    {
                      "position": "SP"
                    },
                    {
                      "position": "RP"
                    },
                    {
                      "position": "P"
                    }
                  ]
                },
                {
                  "eligible_positions_to_add": []
                },
                [],
                [],
                [],
                [],
                []
              ]
            ]
          },
          "19": {
            "player": [
              [
                {
                  "player_key": "458.p.10826"
                },
                {
                  "player_id": "10826"
                },
                {
                  "name": {
                    "full": "Austin Hays",
                    "first": "Austin",
                    "last": "Hays",
                    "ascii_first": "Austin",
                    "ascii_last": "Hays"
                  }
                },
                {
                  "url": "https://sports.yahoo.com/mlb/players/10826"
                },
                {
                  "editorial_player_key": "mlb.p.10826"
                },
                {
                  "editorial_team_key": "mlb.t.17"
                },
                {
                  "editorial_team_full_name": "Cincinnati Reds"
                },
                {
                  "editorial_team_abbr": "CIN"
                },
                {
                  "editorial_team_url": "https://sports.yahoo.com/mlb/teams/cincinnati/"
                },
                {
                  "is_keeper": {
                    "status": false,
                    "cost": false,
                    "kept": false
                  }
                },
                {
                  "uniform_number": "12"
                },
                {
                  "display_position": "OF"
                },
                {
                  "headshot": {
                    "url": "https://s.yimg.com/iu/api/res/1.2/gYj2ssXd4ssmEObuz8UL3w--~C/YXBwaWQ9eXNwb3J0cztjaD0yMzM2O2NyPTE7Y3c9MTc5MDtkeD04NTc7ZHk9MDtmaT11bGNyb3A7aD02MDtxPTEwMDt3PTQ2/https://s.yimg.com/xe/i/us/sp/v/mlb_cutout/players_l/03192025/10826.png",
                    "size": "small"
                  },
                  "image_url": "https://s.yimg.com/iu/api/res/1.2/gYj2ssXd4ssmEObuz8UL3w--~C/YXBwaWQ9eXNwb3J0cztjaD0yMzM2O2NyPTE7Y3c9MTc5MDtkeD04NTc7ZHk9MDtmaT11bGNyb3A7aD02MDtxPTEwMDt3PTQ2/https://s.yimg.com/xe/i/us/sp/v/mlb_cutout/players_l/03192025/10826.png"
                },
                {
                  "is_undroppable": "0"
                },
                {
                  "position_type": "B"
                },
                {
                  "primary_position": "OF"
                },
                {
                  "eligible_positions": [
                    {
                      "position": "OF"
                    },
                    {
                      "position": "Util"
                    }
                  ]
                },
                {
                  "eligible_positions_to_add": []
                },
                [],
                [],
                {
                  "has_player_notes": 1
                },
                [],
                {
                  "player_notes_last_timestamp": 1756725202
                }
              ]
            ]
          },
          "20": {
            "player": [
              [
                {
                  "player_key": "458.p.12367"
                },
                {
                  "player_id": "12367"
                },
                {
                  "name": {
                    "full": "Dylan Dodd",
                    "first": "Dylan",
                    "last": "Dodd",
                    "ascii_first": "Dylan",
                    "ascii_last": "Dodd"
                  }
                },
                {
                  "url": "https://sports.yahoo.com/mlb/players/12367"
                },
                {
                  "editorial_player_key": "mlb.p.12367"
                },
                {
                  "editorial_team_key": "mlb.t.15"
                },
                {
                  "editorial_team_full_name": "Atlanta Braves"
                },
                {
                  "editorial_team_abbr": "ATL"
                },
                {
                  "editorial_team_url": "https://sports.yahoo.com/mlb/teams/atlanta/"
                },
                {
                  "is_keeper": {
                    "status": false,
                    "cost": false,
                    "kept": false
                  }
                },
                {
                  "uniform_number": "46"
                },
                {
                  "display_position": "SP,RP"
                },
                {
                  "headshot": {
                    "url": "https://s.yimg.com/iu/api/res/1.2/dPKGsqNEwVwdfwtaK.23CQ--~C/YXBwaWQ9eXNwb3J0cztjaD0yMzM2O2NyPTE7Y3c9MTc5MDtkeD04NTc7ZHk9MDtmaT11bGNyb3A7aD02MDtxPTEwMDt3PTQ2/https://s.yimg.com/xe/i/us/sp/v/mlb_cutout/players_l/03172023/12367.png",
                    "size": "small"
                  },
                  "image_url": "https://s.yimg.com/iu/api/res/1.2/dPKGsqNEwVwdfwtaK.23CQ--~C/YXBwaWQ9eXNwb3J0cztjaD0yMzM2O2NyPTE7Y3c9MTc5MDtkeD04NTc7ZHk9MDtmaT11bGNyb3A7aD02MDtxPTEwMDt3PTQ2/https://s.yimg.com/xe/i/us/sp/v/mlb_cutout/players_l/03172023/12367.png"
                },
                {
                  "is_undroppable": "0"
                },
                {
                  "position_type": "P"
                },
                {
                  "primary_position": "SP"
                },
                {
                  "eligible_positions": [
                    {
                      "position": "SP"
                    },
                    {
                      "position": "RP"
                    },
                    {
                      "position": "P"
                    }
                  ]
                },
                {
                  "eligible_positions_to_add": []
                },
                [],
                [],
                [],
                [],
                []
              ]
            ]
          },
          "21": {
            "player": [
              [
                {
                  "player_key": "458.p.12093"
                },
                {
                  "player_id": "12093"
                },
                {
                  "name": {
                    "full": "Carlos Vargas",
                    "first": "Carlos",
                    "last": "Vargas",
                    "ascii_first": "Carlos",
                    "ascii_last": "Vargas"
                  }
                },
                {
                  "url": "https://sports.yahoo.com/mlb/players/12093"
                },
                {
                  "editorial_player_key": "mlb.p.12093"
                },
                {
                  "editorial_team_key": "mlb.t.12"
                },
                {
                  "editorial_team_full_name": "Seattle Mariners"
                },
                {
                  "editorial_team_abbr": "SEA"
                },
                {
                  "editorial_team_url": "https://sports.yahoo.com/mlb/teams/seattle/"
                },
                {
                  "is_keeper": {
                    "status": false,
                    "cost": false,
                    "kept": false
                  }
                },
                {
                  "uniform_number": "54"
                },
                {
                  "display_position": "RP"
                },
                {
                  "headshot": {
                    "url": "https://s.yimg.com/iu/api/res/1.2/joWgXVZk1Ec_6vZmrb9C8Q--~C/YXBwaWQ9eXNwb3J0cztjaD0yMzM2O2NyPTE7Y3c9MTc5MDtkeD04NTc7ZHk9MDtmaT11bGNyb3A7aD02MDtxPTEwMDt3PTQ2/https://s.yimg.com/xe/i/us/sp/v/mlb_cutout/players_l/03182025/12093.png",
                    "size": "small"
                  },
                  "image_url": "https://s.yimg.com/iu/api/res/1.2/joWgXVZk1Ec_6vZmrb9C8Q--~C/YXBwaWQ9eXNwb3J0cztjaD0yMzM2O2NyPTE7Y3c9MTc5MDtkeD04NTc7ZHk9MDtmaT11bGNyb3A7aD02MDtxPTEwMDt3PTQ2/https://s.yimg.com/xe/i/us/sp/v/mlb_cutout/players_l/03182025/12093.png"
                },
                {
                  "is_undroppable": "0"
                },
                {
                  "position_type": "P"
                },
                {
                  "primary_position": "RP"
                },
                {
                  "eligible_positions": [
                    {
                      "position": "RP"
                    },
                    {
                      "position": "P"
                    }
                  ]
                },
                {
                  "eligible_positions_to_add": []
                },
                [],
                [],
                {
                  "has_player_notes": 1
                },
                [],
                {
                  "player_notes_last_timestamp": 1756108259
                }
              ]
            ]
          },
          "22": {
            "player": [
              [
                {
                  "player_key": "458.p.10494"
                },
                {
                  "player_id": "10494"
                },
                {
                  "name": {
                    "full": "Jakob Junis",
                    "first": "Jakob",
                    "last": "Junis",
                    "ascii_first": "Jakob",
                    "ascii_last": "Junis"
                  }
                },
                {
                  "url": "https://sports.yahoo.com/mlb/players/10494"
                },
                {
                  "editorial_player_key": "mlb.p.10494"
                },
                {
                  "editorial_team_key": "mlb.t.5"
                },
                {
                  "editorial_team_full_name": "Cleveland Guardians"
                },
                {
                  "editorial_team_abbr": "CLE"
                },
                {
                  "editorial_team_url": "https://sports.yahoo.com/mlb/teams/cleveland/"
                },
                {
                  "is_keeper": {
                    "status": false,
                    "cost": false,
                    "kept": false
                  }
                },
                {
                  "uniform_number": "16"
                },
                {
                  "display_position": "SP,RP"
                },
                {
                  "headshot": {
                    "url": "https://s.yimg.com/iu/api/res/1.2/BvoE73lgERiGXjMqq.kPig--~C/YXBwaWQ9eXNwb3J0cztjaD0yMzM2O2NyPTE7Y3c9MTc5MDtkeD04NTc7ZHk9MDtmaT11bGNyb3A7aD02MDtxPTEwMDt3PTQ2/https://s.yimg.com/xe/i/us/sp/v/mlb_cutout/players_l/03192025/10494.png",
                    "size": "small"
                  },
                  "image_url": "https://s.yimg.com/iu/api/res/1.2/BvoE73lgERiGXjMqq.kPig--~C/YXBwaWQ9eXNwb3J0cztjaD0yMzM2O2NyPTE7Y3c9MTc5MDtkeD04NTc7ZHk9MDtmaT11bGNyb3A7aD02MDtxPTEwMDt3PTQ2/https://s.yimg.com/xe/i/us/sp/v/mlb_cutout/players_l/03192025/10494.png"
                },
                {
                  "is_undroppable": "0"
                },
                {
                  "position_type": "P"
                },
                {
                  "primary_position": "SP"
                },
                {
                  "eligible_positions": [
                    {
                      "position": "SP"
                    },
                    {
                      "position": "RP"
                    },
                    {
                      "position": "P"
                    }
                  ]
                },
                {
                  "eligible_positions_to_add": []
                },
                [],
                [],
                [],
                [],
                []
              ]
            ]
          },
          "23": {
            "player": [
              [
                {
                  "player_key": "458.p.12718"
                },
                {
                  "player_id": "12718"
                },
                {
                  "name": {
                    "full": "Hogan Harris",
                    "first": "Hogan",
                    "last": "Harris",
                    "ascii_first": "Hogan",
                    "ascii_last": "Harris"
                  }
                },
                {
                  "url": "https://sports.yahoo.com/mlb/players/12718"
                },
                {
                  "editorial_player_key": "mlb.p.12718"
                },
                {
                  "editorial_team_key": "mlb.t.11"
                },
                {
                  "editorial_team_full_name": " Athletics"
                },
                {
                  "editorial_team_abbr": "ATH"
                },
                {
                  "editorial_team_url": "https://sports.yahoo.com/mlb/teams/athletics/"
                },
                {
                  "is_keeper": {
                    "status": false,
                    "cost": false,
                    "kept": false
                  }
                },
                {
                  "uniform_number": "36"
                },
                {
                  "display_position": "SP,RP"
                },
                {
                  "headshot": {
                    "url": "https://s.yimg.com/iu/api/res/1.2/KxXiYLS2qyIuIS25Dv5g2g--~C/YXBwaWQ9eXNwb3J0cztjaD0yMzM2O2NyPTE7Y3c9MTc5MDtkeD04NTc7ZHk9MDtmaT11bGNyb3A7aD02MDtxPTEwMDt3PTQ2/https://s.yimg.com/xe/i/us/sp/v/mlb_cutout/players_l/03072025/12718.png",
                    "size": "small"
                  },
                  "image_url": "https://s.yimg.com/iu/api/res/1.2/KxXiYLS2qyIuIS25Dv5g2g--~C/YXBwaWQ9eXNwb3J0cztjaD0yMzM2O2NyPTE7Y3c9MTc5MDtkeD04NTc7ZHk9MDtmaT11bGNyb3A7aD02MDtxPTEwMDt3PTQ2/https://s.yimg.com/xe/i/us/sp/v/mlb_cutout/players_l/03072025/12718.png"
                },
                {
                  "is_undroppable": "0"
                },
                {
                  "position_type": "P"
                },
                {
                  "primary_position": "SP"
                },
                {
                  "eligible_positions": [
                    {
                      "position": "SP"
                    },
                    {
                      "position": "RP"
                    },
                    {
                      "position": "P"
                    }
                  ]
                },
                {
                  "eligible_positions_to_add": []
                },
                [],
                [],
                {
                  "has_player_notes": 1
                },
                [],
                {
                  "player_notes_last_timestamp": 1756653394
                }
              ]
            ]
          },
          "24": {
            "player": [
              [
                {
                  "player_key": "458.p.11326"
                },
                {
                  "player_id": "11326"
                },
                {
                  "name": {
                    "full": "Leo Rivas",
                    "first": "Leo",
                    "last": "Rivas",
                    "ascii_first": "Leo",
                    "ascii_last": "Rivas"
                  }
                },
                {
                  "url": "https://sports.yahoo.com/mlb/players/11326"
                },
                {
                  "editorial_player_key": "mlb.p.11326"
                },
                {
                  "editorial_team_key": "mlb.t.12"
                },
                {
                  "editorial_team_full_name": "Seattle Mariners"
                },
                {
                  "editorial_team_abbr": "SEA"
                },
                {
                  "editorial_team_url": "https://sports.yahoo.com/mlb/teams/seattle/"
                },
                {
                  "is_keeper": {
                    "status": false,
                    "cost": false,
                    "kept": false
                  }
                },
                {
                  "uniform_number": "76"
                },
                {
                  "display_position": "2B,SS"
                },
                {
                  "headshot": {
                    "url": "https://s.yimg.com/iu/api/res/1.2/78fgbJ5qb7V1DFearfc.tQ--~C/YXBwaWQ9eXNwb3J0cztjaD0yMzM2O2NyPTE7Y3c9MTc5MDtkeD04NTc7ZHk9MDtmaT11bGNyb3A7aD02MDtxPTEwMDt3PTQ2/https://s.yimg.com/xe/i/us/sp/v/mlb_cutout/players_l/03182025/11326.png",
                    "size": "small"
                  },
                  "image_url": "https://s.yimg.com/iu/api/res/1.2/78fgbJ5qb7V1DFearfc.tQ--~C/YXBwaWQ9eXNwb3J0cztjaD0yMzM2O2NyPTE7Y3c9MTc5MDtkeD04NTc7ZHk9MDtmaT11bGNyb3A7aD02MDtxPTEwMDt3PTQ2/https://s.yimg.com/xe/i/us/sp/v/mlb_cutout/players_l/03182025/11326.png"
                },
                {
                  "is_undroppable": "0"
                },
                {
                  "position_type": "B"
                },
                {
                  "primary_position": "2B"
                },
                {
                  "eligible_positions": [
                    {
                      "position": "2B"
                    },
                    {
                      "position": "SS"
                    },
                    {
                      "position": "Util"
                    }
                  ]
                },
                {
                  "eligible_positions_to_add": []
                },
                [],
                [],
                {
                  "has_player_notes": 1
                },
                {
                  "has_recent_player_notes": 1
                },
                {
                  "player_notes_last_timestamp": 1756781100
                }
              ]
            ]
          },
          "count": 25
        }
      }
    ],
    "time": "244.47512626648ms",
    "copyright": "Certain Data by Sportradar, Stats Perform and Rotowire",
    "refresh_rate": "60"
  }
}